servicelog.py
setup.py
pysvclog.egg-info/PKG-INFO
pysvclog.egg-info/SOURCES.txt
pysvclog.egg-info/dependency_links.txt
pysvclog.egg-info/top_level.txt
pysvclog.egg-info/zip-safe