Metadata-Version: 1.0
Name: pysvclog
Version: 0.1
Summary: Module to send service logs to JSON UDP collector
Home-page: https://github.com/langloisjp/pysvclog
Author: Jean-Philippe Langlois
Author-email: jpl@jplanglois.com
License: MIT
Platform: UNKNOWN
